acheck/__init__.py
acheck/__main__.py
acheck/checkers.py
acheck/constants.py
acheck/server.py
acheck/checking/__init__.py
acheck/checking/check_interface.py
acheck/checking/error.py
acheck/checking/fixing.py
acheck/checks/__init__.py
acheck/checks/file.py
acheck/checks/objects.py
acheck/checks/signature.py
acheck/checks/spelling.py
acheck/checks/structure.py
acheck/checks/validating.py
acheck/config/__init__.py
acheck/config/config.py
acheck/config/config.toml
acheck/utils/__init__.py
acheck/utils/annotationhelper.py
acheck/utils/filehelper.py
acheck/utils/htmlhelper.py
acheck/utils/loghelper.py
acheck/utils/parsing.py
acheck/utils/typecheck.py
docs/conf.py
resources/__init__.py
resources/editor.css
resources/editor.html
resources/editor.js
resources/favicon.ico
resources/universitaet_rostock_logo.jpg
resources/vac_logo.png
resources/ace/__init__.py
resources/ace/ace.js
resources/ace/ext-beautify.js
resources/ace/mode-pddl.js
acheck-0.0.17.dist-info/METADATA
acheck-0.0.17.dist-info/WHEEL
acheck-0.0.17.dist-info/entry_points.txt
acheck-0.0.17.dist-info/top_level.txt
acheck-0.0.17.dist-info/RECORD
