Metadata-Version: 2.1
Name: acheck
Version: 0.0.17
Summary: Causal Annotation Correction Tool
Author-email: Felix Gratzkowski <felix.gratzkowski@uni-rostock.de>
License: CC-BY-NC-SA-4.0
Classifier: Development Status :: 3 - Alpha
Classifier: Programming Language :: Python
Classifier: Programming Language :: Python :: 3
Requires-Python: >=3.9
Requires-Dist: antlr4-python3-runtime==4.9.3
Requires-Dist: pddlpy==0.3.3
Requires-Dist: pyenchant==3.2.2
Requires-Dist: toml==0.10.2
Requires-Dist: requests==2.31.0
Requires-Dist: docutils==0.18.1
Requires-Dist: pddl==0.4.1
